{"daily_drawdown": [{"date": "2010-06-01", "drawdown_pct": 0.0}, {"date": "2010-06-08", "drawdown_pct": -0.22}, {"date": "2010-06-18", "drawdown_pct": -10.86}, {"date": "2010-06-25", "drawdown_pct": -9.44}, {"date": "2010-07-02", "drawdown_pct": -22.2}, {"date": "2010-07-09", "drawdown_pct": -16.94}, {"date": "2010-07-16", "drawdown_pct": -20.49}, {"date": "2010-07-23", "drawdown_pct": -14.4}, {"date": "2010-07-30", "drawdown_pct": -13.7}, {"date": "2010-08-06", "drawdown_pct": -9.87}, {"date": "2010-08-13", "drawdown_pct": -10.25}, {"date": "2010-08-20", "drawdown_pct": -11.25}, {"date": "2010-08-27", "drawdown_pct": -10.94}, {"date": "2010-09-03", "drawdown_pct": -7.62}, {"date": "2010-09-10", "drawdown_pct": -7.78}, {"date": "2010-09-17", "drawdown_pct": -13.36}, {"date": "2010-09-29", "drawdown_pct": -17.42}, {"date": "2010-10-13", "drawdown_pct": -14.21}, {"date": "2010-10-20", "drawdown_pct": -10.48}, {"date": "2010-10-27", "drawdown_pct": -8.16}, {"date": "2010-11-03", "drawdown_pct": -7.27}, {"date": "2010-11-10", "drawdown_pct": 0.0}, {"date": "2010-11-17", "drawdown_pct": -5.5}, {"date": "2010-11-24", "drawdown_pct": 0.0}, {"date": "2010-12-01", "drawdown_pct": -3.52}, {"date": "2010-12-08", "drawdown_pct": -4.91}, {"date": "2010-12-15", "drawdown_pct": -0.68}, {"date": "2010-12-22", "drawdown_pct": -2.54}, {"date": "2010-12-29", "drawdown_pct": -9.71}, {"date": "2011-01-06", "drawdown_pct": -7.96}, {"date": "2011-01-13", "drawdown_pct": -11.28}, {"date": "2011-01-20", "drawdown_pct": -17.24}, {"date": "2011-01-27", "drawdown_pct": -17.84}, {"date": "2011-02-10", "drawdown_pct": -13.71}, {"date": "2011-02-17", "drawdown_pct": -9.54}, {"date": "2011-02-24", "drawdown_pct": -10.63}, {"date": "2011-03-03", "drawdown_pct": -13.68}, {"date": "2011-03-10", "drawdown_pct": -11.28}, {"date": "2011-03-17", "drawdown_pct": -12.54}, {"date": "2011-03-24", "drawdown_pct": -12.57}, {"date": "2011-03-31", "drawdown_pct": -18.22}, {"date": "2011-04-11", "drawdown_pct": -18.67}, {"date": "2011-04-18", "drawdown_pct": -18.63}, {"date": "2011-04-25", "drawdown_pct": -20.91}, {"date": "2011-05-03", "drawdown_pct": -25.22}, {"date": "2011-05-10", "drawdown_pct": -24.47}, {"date": "2011-05-17", "drawdown_pct": -27.4}, {"date": "2011-05-24", "drawdown_pct": -29.36}, {"date": "2011-05-31", "drawdown_pct": -31.36}, {"date": "2011-06-08", "drawdown_pct": -31.47}, {"date": "2011-06-15", "drawdown_pct": -32.88}, {"date": "2011-06-22", "drawdown_pct": -35.81}, {"date": "2011-06-29", "drawdown_pct": -32.17}, {"date": "2011-07-06", "drawdown_pct": -27.47}, {"date": "2011-07-13", "drawdown_pct": -25.94}, {"date": "2011-07-20", "drawdown_pct": -24.51}, {"date": "2011-07-27", "drawdown_pct": -25.74}, {"date": "2011-08-03", "drawdown_pct": -23.32}, {"date": "2011-08-10", "drawdown_pct": -27.68}, {"date": "2011-08-17", "drawdown_pct": -24.07}, {"date": "2011-08-24", "drawdown_pct": -23.75}, {"date": "2011-08-31", "drawdown_pct": -25.26}, {"date": "2011-09-07", "drawdown_pct": -27.04}, {"date": "2011-09-15", "drawdown_pct": -28.96}, {"date": "2011-09-22", "drawdown_pct": -30.82}, {"date": "2011-09-29", "drawdown_pct": -35.77}, {"date": "2011-10-13", "drawdown_pct": -32.44}, {"date": "2011-10-20", "drawdown_pct": -36.82}, {"date": "2011-10-27", "drawdown_pct": -34.23}, {"date": "2011-11-03", "drawdown_pct": -28.82}, {"date": "2011-11-10", "drawdown_pct": -27.39}, {"date": "2011-11-17", "drawdown_pct": -27.14}, {"date": "2011-11-24", "drawdown_pct": -29.59}, {"date": "2011-12-01", "drawdown_pct": -30.83}, {"date": "2011-12-08", "drawdown_pct": -34.35}, {"date": "2011-12-15", "drawdown_pct": -39.45}, {"date": "2011-12-22", "drawdown_pct": -38.53}, {"date": "2011-12-29", "drawdown_pct": -41.88}, {"date": "2012-01-09", "drawdown_pct": -43.84}, {"date": "2012-01-16", "drawdown_pct": -48.59}, {"date": "2012-01-30", "drawdown_pct": -47.18}, {"date": "2012-02-06", "drawdown_pct": -44.32}, {"date": "2012-02-13", "drawdown_pct": -42.01}, {"date": "2012-02-20", "drawdown_pct": -41.52}, {"date": "2012-02-27", "drawdown_pct": -38.33}, {"date": "2012-03-05", "drawdown_pct": -38.41}, {"date": "2012-03-12", "drawdown_pct": -36.25}, {"date": "2012-03-19", "drawdown_pct": -36.77}, {"date": "2012-03-26", "drawdown_pct": -40.21}, {"date": "2012-04-05", "drawdown_pct": -43.41}, {"date": "2012-04-12", "drawdown_pct": -42.16}, {"date": "2012-04-19", "drawdown_pct": -41.19}, {"date": "2012-04-26", "drawdown_pct": -44.98}, {"date": "2012-05-07", "drawdown_pct": -40.55}, {"date": "2012-05-14", "drawdown_pct": -41.62}, {"date": "2012-05-21", "drawdown_pct": -42.84}, {"date": "2012-05-28", "drawdown_pct": -42.7}, {"date": "2012-06-04", "drawdown_pct": -41.84}, {"date": "2012-06-11", "drawdown_pct": -40.43}, {"date": "2012-06-18", "drawdown_pct": -38.93}, {"date": "2012-06-26", "drawdown_pct": -41.94}, {"date": "2012-07-03", "drawdown_pct": -39.67}, {"date": "2012-07-10", "drawdown_pct": -42.13}, {"date": "2012-07-17", "drawdown_pct": -43.47}, {"date": "2012-07-24", "drawdown_pct": -42.71}, {"date": "2012-07-31", "drawdown_pct": -45.1}, {"date": "2012-08-07", "drawdown_pct": -40.31}, {"date": "2012-08-14", "drawdown_pct": -40.28}, {"date": "2012-08-21", "drawdown_pct": -39.26}, {"date": "2012-08-28", "drawdown_pct": -40.99}, {"date": "2012-09-04", "drawdown_pct": -41.38}, {"date": "2012-09-11", "drawdown_pct": -38.22}, {"date": "2012-09-18", "drawdown_pct": -41.31}, {"date": "2012-09-25", "drawdown_pct": -44.66}, {"date": "2012-10-09", "drawdown_pct": -42.2}, {"date": "2012-10-16", "drawdown_pct": -42.79}, {"date": "2012-10-23", "drawdown_pct": -42.31}, {"date": "2012-10-30", "drawdown_pct": -44.07}, {"date": "2012-11-06", "drawdown_pct": -44.0}, {"date": "2012-11-13", "drawdown_pct": -45.88}, {"date": "2012-11-20", "drawdown_pct": -46.75}, {"date": "2012-11-27", "drawdown_pct": -50.02}, {"date": "2012-12-04", "drawdown_pct": -51.27}, {"date": "2012-12-11", "drawdown_pct": -48.0}, {"date": "2012-12-18", "drawdown_pct": -47.6}, {"date": "2012-12-25", "drawdown_pct": -43.7}, {"date": "2013-01-04", "drawdown_pct": -42.79}, {"date": "2013-01-11", "drawdown_pct": -40.66}, {"date": "2013-01-18", "drawdown_pct": -36.14}, {"date": "2013-01-25", "drawdown_pct": -38.13}, {"date": "2013-02-01", "drawdown_pct": -36.55}, {"date": "2013-02-08", "drawdown_pct": -33.25}, {"date": "2013-02-22", "drawdown_pct": -31.97}, {"date": "2013-03-01", "drawdown_pct": -28.23}, {"date": "2013-03-08", "drawdown_pct": -29.87}, {"date": "2013-03-15", "drawdown_pct": -30.74}, {"date": "2013-03-22", "drawdown_pct": -28.47}, {"date": "2013-03-29", "drawdown_pct": -29.73}, {"date": "2013-04-09", "drawdown_pct": -30.09}, {"date": "2013-04-16", "drawdown_pct": -31.38}, {"date": "2013-04-23", "drawdown_pct": -27.51}, {"date": "2013-05-03", "drawdown_pct": -23.83}, {"date": "2013-05-10", "drawdown_pct": -19.84}, {"date": "2013-05-17", "drawdown_pct": -17.0}, {"date": "2013-05-24", "drawdown_pct": -12.91}, {"date": "2013-05-31", "drawdown_pct": -12.97}, {"date": "2013-06-07", "drawdown_pct": -16.45}, {"date": "2013-06-19", "drawdown_pct": -13.41}, {"date": "2013-06-26", "drawdown_pct": -15.73}, {"date": "2013-07-03", "drawdown_pct": -10.41}, {"date": "2013-07-10", "drawdown_pct": -13.31}, {"date": "2013-07-17", "drawdown_pct": -8.39}, {"date": "2013-07-24", "drawdown_pct": -2.41}, {"date": "2013-07-31", "drawdown_pct": -8.03}, {"date": "2013-08-07", "drawdown_pct": -4.65}, {"date": "2013-08-14", "drawdown_pct": -4.24}, {"date": "2013-08-21", "drawdown_pct": -4.19}, {"date": "2013-08-28", "drawdown_pct": -1.82}, {"date": "2013-09-04", "drawdown_pct": -1.15}, {"date": "2013-09-11", "drawdown_pct": -4.84}, {"date": "2013-09-18", "drawdown_pct": 0.0}, {"date": "2013-09-27", "drawdown_pct": -0.35}, {"date": "2013-10-11", "drawdown_pct": -2.54}, {"date": "2013-10-18", "drawdown_pct": -4.65}, {"date": "2013-10-25", "drawdown_pct": -10.36}, {"date": "2013-11-01", "drawdown_pct": -13.69}, {"date": "2013-11-08", "drawdown_pct": -14.46}, {"date": "2013-11-15", "drawdown_pct": -10.37}, {"date": "2013-11-22", "drawdown_pct": -8.53}, {"date": "2013-11-29", "drawdown_pct": -3.46}, {"date": "2013-12-06", "drawdown_pct": -14.77}, {"date": "2013-12-13", "drawdown_pct": -9.73}, {"date": "2013-12-20", "drawdown_pct": -11.45}, {"date": "2013-12-27", "drawdown_pct": -8.58}, {"date": "2014-01-06", "drawdown_pct": -6.53}, {"date": "2014-01-13", "drawdown_pct": -3.75}, {"date": "2014-01-20", "drawdown_pct": -3.04}, {"date": "2014-01-27", "drawdown_pct": -0.46}, {"date": "2014-02-10", "drawdown_pct": 0.0}, {"date": "2014-02-17", "drawdown_pct": 0.0}, {"date": "2014-02-24", "drawdown_pct": -1.19}, {"date": "2014-03-03", "drawdown_pct": -6.0}, {"date": "2014-03-10", "drawdown_pct": -9.72}, {"date": "2014-03-17", "drawdown_pct": -5.21}, {"date": "2014-03-24", "drawdown_pct": -10.35}, {"date": "2014-03-31", "drawdown_pct": -14.81}, {"date": "2014-04-08", "drawdown_pct": -13.31}, {"date": "2014-04-15", "drawdown_pct": -12.11}, {"date": "2014-04-22", "drawdown_pct": -14.27}, {"date": "2014-04-29", "drawdown_pct": -18.74}, {"date": "2014-05-08", "drawdown_pct": -17.89}, {"date": "2014-05-15", "drawdown_pct": -19.55}, {"date": "2014-05-22", "drawdown_pct": -18.55}, {"date": "2014-05-29", "drawdown_pct": -15.68}, {"date": "2014-06-06", "drawdown_pct": -13.36}, {"date": "2014-06-13", "drawdown_pct": -11.28}, {"date": "2014-06-20", "drawdown_pct": -14.41}, {"date": "2014-06-27", "drawdown_pct": -10.89}, {"date": "2014-07-04", "drawdown_pct": -9.43}, {"date": "2014-07-11", "drawdown_pct": -12.79}, {"date": "2014-07-18", "drawdown_pct": -16.21}, {"date": "2014-07-25", "drawdown_pct": -17.51}, {"date": "2014-08-01", "drawdown_pct": -14.93}, {"date": "2014-08-08", "drawdown_pct": -11.62}, {"date": "2014-08-15", "drawdown_pct": -10.66}, {"date": "2014-08-22", "drawdown_pct": -6.22}, {"date": "2014-08-29", "drawdown_pct": -8.61}, {"date": "2014-09-05", "drawdown_pct": -4.41}, {"date": "2014-09-15", "drawdown_pct": -2.08}, {"date": "2014-09-22", "drawdown_pct": -4.83}, {"date": "2014-09-29", "drawdown_pct": -2.08}, {"date": "2014-10-13", "drawdown_pct": -0.82}, {"date": "2014-10-20", "drawdown_pct": -1.84}, {"date": "2014-10-27", "drawdown_pct": -4.43}, {"date": "2014-11-03", "drawdown_pct": -2.0}, {"date": "2014-11-10", "drawdown_pct": -2.97}, {"date": "2014-11-17", "drawdown_pct": -5.73}, {"date": "2014-11-24", "drawdown_pct": -3.42}, {"date": "2014-12-01", "drawdown_pct": -1.18}, {"date": "2014-12-08", "drawdown_pct": -3.37}, {"date": "2014-12-15", "drawdown_pct": 0.0}, {"date": "2014-12-22", "drawdown_pct": -8.42}, {"date": "2014-12-29", "drawdown_pct": -9.54}, {"date": "2015-01-07", "drawdown_pct": -8.09}, {"date": "2015-01-14", "drawdown_pct": -4.19}, {"date": "2015-01-21", "drawdown_pct": 0.0}, {"date": "2015-01-28", "drawdown_pct": -0.72}, {"date": "2015-02-04", "drawdown_pct": 0.0}, {"date": "2015-02-11", "drawdown_pct": -0.08}, {"date": "2015-02-25", "drawdown_pct": -1.05}, {"date": "2015-03-04", "drawdown_pct": 0.0}, {"date": "2015-03-11", "drawdown_pct": -0.46}, {"date": "2015-03-18", "drawdown_pct": 0.0}, {"date": "2015-03-25", "drawdown_pct": 0.0}, {"date": "2015-04-01", "drawdown_pct": 0.0}, {"date": "2015-04-09", "drawdown_pct": -2.35}, {"date": "2015-04-16", "drawdown_pct": -3.63}, {"date": "2015-04-23", "drawdown_pct": 0.0}, {"date": "2015-04-30", "drawdown_pct": 0.0}, {"date": "2015-05-08", "drawdown_pct": 0.0}, {"date": "2015-05-15", "drawdown_pct": -3.23}, {"date": "2015-05-22", "drawdown_pct": -0.31}, {"date": "2015-05-29", "drawdown_pct": -2.37}, {"date": "2015-06-05", "drawdown_pct": -2.42}, {"date": "2015-06-12", "drawdown_pct": -2.07}, {"date": "2015-06-19", "drawdown_pct": -16.76}, {"date": "2015-06-29", "drawdown_pct": -32.46}, {"date": "2015-07-06", "drawdown_pct": -37.38}, {"date": "2015-07-13", "drawdown_pct": -32.62}, {"date": "2015-07-20", "drawdown_pct": -28.48}, {"date": "2015-07-27", "drawdown_pct": -32.61}, {"date": "2015-08-03", "drawdown_pct": -39.75}, {"date": "2015-08-10", "drawdown_pct": -32.03}, {"date": "2015-08-17", "drawdown_pct": -33.05}, {"date": "2015-08-24", "drawdown_pct": -45.94}, {"date": "2015-08-31", "drawdown_pct": -49.86}, {"date": "2015-09-09", "drawdown_pct": -47.98}, {"date": "2015-09-16", "drawdown_pct": -51.63}, {"date": "2015-09-23", "drawdown_pct": -47.82}, {"date": "2015-09-30", "drawdown_pct": -47.7}, {"date": "2015-10-14", "drawdown_pct": -42.12}, {"date": "2015-10-21", "drawdown_pct": -41.12}, {"date": "2015-10-28", "drawdown_pct": -37.59}, {"date": "2015-11-04", "drawdown_pct": -35.1}, {"date": "2015-11-11", "drawdown_pct": -29.57}, {"date": "2015-11-18", "drawdown_pct": -33.17}, {"date": "2015-11-25", "drawdown_pct": -27.24}, {"date": "2015-12-02", "drawdown_pct": -34.38}, {"date": "2015-12-09", "drawdown_pct": -33.0}, {"date": "2015-12-16", "drawdown_pct": -30.61}, {"date": "2015-12-23", "drawdown_pct": -30.09}, {"date": "2015-12-30", "drawdown_pct": -30.2}, {"date": "2016-01-07", "drawdown_pct": -43.34}, {"date": "2016-01-14", "drawdown_pct": -45.38}, {"date": "2016-01-21", "drawdown_pct": -46.95}, {"date": "2016-01-28", "drawdown_pct": -52.13}, {"date": "2016-02-04", "drawdown_pct": -46.6}, {"date": "2016-02-18", "drawdown_pct": -44.98}, {"date": "2016-02-25", "drawdown_pct": -48.84}, {"date": "2016-03-03", "drawdown_pct": -49.6}, {"date": "2016-03-10", "drawdown_pct": -51.36}, {"date": "2016-03-17", "drawdown_pct": -47.59}, {"date": "2016-03-24", "drawdown_pct": -44.26}, {"date": "2016-03-31", "drawdown_pct": -43.79}, {"date": "2016-04-08", "drawdown_pct": -44.0}, {"date": "2016-04-15", "drawdown_pct": -42.0}, {"date": "2016-04-22", "drawdown_pct": -46.34}, {"date": "2016-04-29", "drawdown_pct": -46.29}, {"date": "2016-05-09", "drawdown_pct": -48.43}, {"date": "2016-05-16", "drawdown_pct": -48.32}, {"date": "2016-05-23", "drawdown_pct": -47.31}, {"date": "2016-05-30", "drawdown_pct": -48.31}, {"date": "2016-06-06", "drawdown_pct": -44.77}, {"date": "2016-06-15", "drawdown_pct": -46.54}, {"date": "2016-06-22", "drawdown_pct": -46.14}, {"date": "2016-06-29", "drawdown_pct": -44.51}, {"date": "2016-07-06", "drawdown_pct": -43.71}, {"date": "2016-07-13", "drawdown_pct": -42.61}, {"date": "2016-07-20", "drawdown_pct": -43.03}, {"date": "2016-07-27", "drawdown_pct": -45.88}, {"date": "2016-08-03", "drawdown_pct": -47.06}, {"date": "2016-08-10", "drawdown_pct": -46.34}, {"date": "2016-08-17", "drawdown_pct": -44.55}, {"date": "2016-08-24", "drawdown_pct": -44.95}, {"date": "2016-08-31", "drawdown_pct": -44.96}, {"date": "2016-09-07", "drawdown_pct": -44.45}, {"date": "2016-09-14", "drawdown_pct": -46.15}, {"date": "2016-09-23", "drawdown_pct": -45.85}, {"date": "2016-09-30", "drawdown_pct": -46.01}, {"date": "2016-10-14", "drawdown_pct": -44.9}, {"date": "2016-10-21", "drawdown_pct": -45.23}, {"date": "2016-10-28", "drawdown_pct": -45.62}, {"date": "2016-11-04", "drawdown_pct": -46.13}, {"date": "2016-11-11", "drawdown_pct": -46.08}, {"date": "2016-11-18", "drawdown_pct": -45.81}, {"date": "2016-11-25", "drawdown_pct": -45.57}, {"date": "2016-12-02", "drawdown_pct": -46.17}, {"date": "2016-12-09", "drawdown_pct": -47.27}, {"date": "2016-12-16", "drawdown_pct": -49.82}, {"date": "2016-12-23", "drawdown_pct": -50.67}, {"date": "2016-12-30", "drawdown_pct": -50.73}, {"date": "2017-01-09", "drawdown_pct": -50.74}, {"date": "2017-01-16", "drawdown_pct": -54.02}, {"date": "2017-01-23", "drawdown_pct": -52.61}, {"date": "2017-02-06", "drawdown_pct": -52.28}, {"date": "2017-02-13", "drawdown_pct": -51.94}, {"date": "2017-02-20", "drawdown_pct": -52.41}, {"date": "2017-02-27", "drawdown_pct": -51.62}, {"date": "2017-03-06", "drawdown_pct": -50.71}, {"date": "2017-03-13", "drawdown_pct": -50.51}, {"date": "2017-03-20", "drawdown_pct": -50.94}, {"date": "2017-03-27", "drawdown_pct": -51.09}, {"date": "2017-04-05", "drawdown_pct": -51.2}, {"date": "2017-04-12", "drawdown_pct": -52.35}, {"date": "2017-04-19", "drawdown_pct": -53.66}, {"date": "2017-04-26", "drawdown_pct": -54.29}, {"date": "2017-05-04", "drawdown_pct": -53.84}, {"date": "2017-05-11", "drawdown_pct": -55.49}, {"date": "2017-05-18", "drawdown_pct": -54.46}, {"date": "2017-05-25", "drawdown_pct": -55.36}, {"date": "2017-06-05", "drawdown_pct": -55.77}, {"date": "2017-06-12", "drawdown_pct": -55.41}, {"date": "2017-06-19", "drawdown_pct": -54.39}, {"date": "2017-06-26", "drawdown_pct": -54.27}, {"date": "2017-07-03", "drawdown_pct": -53.9}, {"date": "2017-07-10", "drawdown_pct": -54.72}, {"date": "2017-07-17", "drawdown_pct": -58.4}, {"date": "2017-07-24", "drawdown_pct": -57.65}, {"date": "2017-07-31", "drawdown_pct": -56.4}, {"date": "2017-08-07", "drawdown_pct": -56.5}, {"date": "2017-08-14", "drawdown_pct": -54.96}, {"date": "2017-08-21", "drawdown_pct": -54.07}, {"date": "2017-08-28", "drawdown_pct": -53.72}, {"date": "2017-09-04", "drawdown_pct": -52.7}, {"date": "2017-09-11", "drawdown_pct": -52.38}, {"date": "2017-09-18", "drawdown_pct": -52.42}, {"date": "2017-09-25", "drawdown_pct": -53.7}, {"date": "2017-10-09", "drawdown_pct": -52.54}, {"date": "2017-10-16", "drawdown_pct": -52.72}, {"date": "2017-10-23", "drawdown_pct": -52.32}, {"date": "2017-10-30", "drawdown_pct": -53.39}, {"date": "2017-11-06", "drawdown_pct": -53.54}, {"date": "2017-11-13", "drawdown_pct": -52.13}, {"date": "2017-11-20", "drawdown_pct": -53.3}, {"date": "2017-11-27", "drawdown_pct": -55.78}, {"date": "2017-12-04", "drawdown_pct": -54.86}, {"date": "2017-12-11", "drawdown_pct": -54.37}, {"date": "2017-12-18", "drawdown_pct": -55.29}, {"date": "2017-12-25", "drawdown_pct": -55.91}, {"date": "2018-01-02", "drawdown_pct": -55.56}, {"date": "2018-01-09", "drawdown_pct": -54.71}, {"date": "2018-01-16", "drawdown_pct": -56.57}, {"date": "2018-01-23", "drawdown_pct": -55.61}, {"date": "2018-01-30", "drawdown_pct": -55.24}, {"date": "2018-02-06", "drawdown_pct": -59.87}, {"date": "2018-02-13", "drawdown_pct": -58.6}, {"date": "2018-02-27", "drawdown_pct": -56.22}, {"date": "2018-03-06", "drawdown_pct": -54.86}, {"date": "2018-03-13", "drawdown_pct": -52.97}, {"date": "2018-03-20", "drawdown_pct": -53.18}, {"date": "2018-03-27", "drawdown_pct": -53.68}, {"date": "2018-04-03", "drawdown_pct": -52.98}, {"date": "2018-04-12", "drawdown_pct": -54.12}, {"date": "2018-04-19", "drawdown_pct": -54.29}, {"date": "2018-04-26", "drawdown_pct": -55.27}, {"date": "2018-05-07", "drawdown_pct": -53.49}, {"date": "2018-05-14", "drawdown_pct": -54.02}, {"date": "2018-05-21", "drawdown_pct": -53.23}, {"date": "2018-05-28", "drawdown_pct": -54.88}, {"date": "2018-06-04", "drawdown_pct": -57.24}, {"date": "2018-06-11", "drawdown_pct": -57.6}, {"date": "2018-06-19", "drawdown_pct": -61.15}, {"date": "2018-06-26", "drawdown_pct": -60.7}, {"date": "2018-07-03", "drawdown_pct": -59.64}, {"date": "2018-07-10", "drawdown_pct": -60.0}, {"date": "2018-07-17", "drawdown_pct": -59.28}, {"date": "2018-07-24", "drawdown_pct": -59.08}, {"date": "2018-07-31", "drawdown_pct": -60.79}, {"date": "2018-08-07", "drawdown_pct": -62.85}, {"date": "2018-08-14", "drawdown_pct": -61.87}, {"date": "2018-08-21", "drawdown_pct": -63.41}, {"date": "2018-08-28", "drawdown_pct": -62.51}, {"date": "2018-09-04", "drawdown_pct": -63.45}, {"date": "2018-09-11", "drawdown_pct": -64.97}, {"date": "2018-09-18", "drawdown_pct": -65.41}, {"date": "2018-09-26", "drawdown_pct": -64.32}, {"date": "2018-10-10", "drawdown_pct": -66.18}, {"date": "2018-10-17", "drawdown_pct": -69.07}, {"date": "2018-10-24", "drawdown_pct": -67.75}, {"date": "2018-10-31", "drawdown_pct": -67.97}, {"date": "2018-11-07", "drawdown_pct": -66.21}, {"date": "2018-11-14", "drawdown_pct": -65.2}, {"date": "2018-11-21", "drawdown_pct": -65.77}, {"date": "2018-11-28", "drawdown_pct": -66.32}, {"date": "2018-12-05", "drawdown_pct": -65.3}, {"date": "2018-12-12", "drawdown_pct": -66.38}, {"date": "2018-12-19", "drawdown_pct": -68.14}, {"date": "2018-12-26", "drawdown_pct": -68.26}, {"date": "2019-01-04", "drawdown_pct": -68.73}, {"date": "2019-01-11", "drawdown_pct": -68.32}, {"date": "2019-01-18", "drawdown_pct": -68.12}, {"date": "2019-01-25", "drawdown_pct": -68.22}, {"date": "2019-02-01", "drawdown_pct": -68.08}, {"date": "2019-02-15", "drawdown_pct": -65.9}, {"date": "2019-02-22", "drawdown_pct": -63.43}, {"date": "2019-03-01", "drawdown_pct": -60.63}, {"date": "2019-03-08", "drawdown_pct": -58.45}, {"date": "2019-03-15", "drawdown_pct": -58.25}, {"date": "2019-03-22", "drawdown_pct": -57.46}, {"date": "2019-03-29", "drawdown_pct": -57.47}, {"date": "2019-04-08", "drawdown_pct": -56.31}, {"date": "2019-04-15", "drawdown_pct": -58.14}, {"date": "2019-04-22", "drawdown_pct": -57.37}, {"date": "2019-04-29", "drawdown_pct": -59.43}, {"date": "2019-05-09", "drawdown_pct": -63.1}, {"date": "2019-05-16", "drawdown_pct": -61.49}, {"date": "2019-05-23", "drawdown_pct": -63.56}, {"date": "2019-05-30", "drawdown_pct": -62.7}, {"date": "2019-06-06", "drawdown_pct": -64.44}, {"date": "2019-06-14", "drawdown_pct": -63.49}, {"date": "2019-06-21", "drawdown_pct": -61.73}, {"date": "2019-06-28", "drawdown_pct": -62.04}, {"date": "2019-07-05", "drawdown_pct": -61.13}, {"date": "2019-07-12", "drawdown_pct": -61.88}, {"date": "2019-07-19", "drawdown_pct": -61.28}, {"date": "2019-07-26", "drawdown_pct": -60.78}, {"date": "2019-08-02", "drawdown_pct": -60.91}, {"date": "2019-08-09", "drawdown_pct": -62.14}, {"date": "2019-08-16", "drawdown_pct": -60.63}, {"date": "2019-08-23", "drawdown_pct": -59.43}, {"date": "2019-08-30", "drawdown_pct": -59.55}, {"date": "2019-09-06", "drawdown_pct": -57.51}, {"date": "2019-09-16", "drawdown_pct": -56.95}, {"date": "2019-09-23", "drawdown_pct": -57.7}, {"date": "2019-09-30", "drawdown_pct": -59.13}, {"date": "2019-10-14", "drawdown_pct": -57.83}, {"date": "2019-10-21", "drawdown_pct": -58.7}, {"date": "2019-10-28", "drawdown_pct": -57.2}, {"date": "2019-11-04", "drawdown_pct": -57.31}, {"date": "2019-11-11", "drawdown_pct": -57.99}, {"date": "2019-11-18", "drawdown_pct": -57.75}, {"date": "2019-11-25", "drawdown_pct": -58.27}, {"date": "2019-12-02", "drawdown_pct": -58.08}, {"date": "2019-12-09", "drawdown_pct": -56.78}, {"date": "2019-12-16", "drawdown_pct": -55.29}, {"date": "2019-12-23", "drawdown_pct": -56.39}, {"date": "2019-12-30", "drawdown_pct": -55.04}, {"date": "2020-01-07", "drawdown_pct": -52.46}, {"date": "2020-01-14", "drawdown_pct": -51.72}, {"date": "2020-01-21", "drawdown_pct": -50.61}, {"date": "2020-02-05", "drawdown_pct": -51.29}, {"date": "2020-02-12", "drawdown_pct": -47.64}, {"date": "2020-02-19", "drawdown_pct": -46.28}, {"date": "2020-02-26", "drawdown_pct": -45.24}, {"date": "2020-03-04", "drawdown_pct": -45.52}, {"date": "2020-03-11", "drawdown_pct": -47.23}, {"date": "2020-03-18", "drawdown_pct": -52.61}, {"date": "2020-03-25", "drawdown_pct": -51.34}, {"date": "2020-04-01", "drawdown_pct": -53.17}, {"date": "2020-04-09", "drawdown_pct": -49.85}, {"date": "2020-04-16", "drawdown_pct": -49.57}, {"date": "2020-04-23", "drawdown_pct": -49.04}, {"date": "2020-04-30", "drawdown_pct": -48.03}, {"date": "2020-05-12", "drawdown_pct": -46.66}, {"date": "2020-05-19", "drawdown_pct": -46.16}, {"date": "2020-05-26", "drawdown_pct": -46.94}, {"date": "2020-06-02", "drawdown_pct": -46.13}, {"date": "2020-06-09", "drawdown_pct": -45.22}, {"date": "2020-06-16", "drawdown_pct": -43.24}, {"date": "2020-06-23", "drawdown_pct": -40.18}, {"date": "2020-07-02", "drawdown_pct": -39.12}, {"date": "2020-07-09", "drawdown_pct": -30.75}, {"date": "2020-07-16", "drawdown_pct": -33.55}, {"date": "2020-07-23", "drawdown_pct": -29.7}, {"date": "2020-07-30", "drawdown_pct": -31.1}, {"date": "2020-08-06", "drawdown_pct": -29.33}, {"date": "2020-08-13", "drawdown_pct": -34.14}, {"date": "2020-08-20", "drawdown_pct": -35.02}, {"date": "2020-08-27", "drawdown_pct": -32.47}, {"date": "2020-09-03", "drawdown_pct": -31.02}, {"date": "2020-09-10", "drawdown_pct": -37.65}, {"date": "2020-09-17", "drawdown_pct": -35.78}, {"date": "2020-09-24", "drawdown_pct": -36.32}, {"date": "2020-10-09", "drawdown_pct": -32.88}, {"date": "2020-10-16", "drawdown_pct": -31.58}, {"date": "2020-10-23", "drawdown_pct": -34.69}, {"date": "2020-10-30", "drawdown_pct": -33.31}, {"date": "2020-11-06", "drawdown_pct": -31.37}, {"date": "2020-11-13", "drawdown_pct": -32.03}, {"date": "2020-11-20", "drawdown_pct": -33.03}, {"date": "2020-11-27", "drawdown_pct": -34.23}, {"date": "2020-12-04", "drawdown_pct": -31.42}, {"date": "2020-12-11", "drawdown_pct": -32.51}, {"date": "2020-12-18", "drawdown_pct": -30.17}, {"date": "2020-12-25", "drawdown_pct": -28.66}, {"date": "2021-01-04", "drawdown_pct": -22.7}, {"date": "2021-01-11", "drawdown_pct": -22.33}, {"date": "2021-01-18", "drawdown_pct": -20.92}, {"date": "2021-01-25", "drawdown_pct": -15.75}, {"date": "2021-02-01", "drawdown_pct": -20.65}, {"date": "2021-02-08", "drawdown_pct": -17.68}, {"date": "2021-02-22", "drawdown_pct": -21.18}, {"date": "2021-03-01", "drawdown_pct": -24.8}, {"date": "2021-03-08", "drawdown_pct": -31.47}, {"date": "2021-03-15", "drawdown_pct": -33.61}, {"date": "2021-03-22", "drawdown_pct": -32.24}, {"date": "2021-03-29", "drawdown_pct": -31.35}, {"date": "2021-04-06", "drawdown_pct": -28.89}, {"date": "2021-04-13", "drawdown_pct": -31.12}, {"date": "2021-04-20", "drawdown_pct": -27.27}, {"date": "2021-04-27", "drawdown_pct": -25.02}, {"date": "2021-05-07", "drawdown_pct": -26.92}, {"date": "2021-05-14", "drawdown_pct": -23.82}, {"date": "2021-05-21", "drawdown_pct": -21.82}, {"date": "2021-05-28", "drawdown_pct": -18.83}, {"date": "2021-06-04", "drawdown_pct": -18.57}, {"date": "2021-06-11", "drawdown_pct": -17.17}, {"date": "2021-06-21", "drawdown_pct": -17.87}, {"date": "2021-06-28", "drawdown_pct": -14.3}, {"date": "2021-07-05", "drawdown_pct": -15.82}, {"date": "2021-07-12", "drawdown_pct": -11.24}, {"date": "2021-07-19", "drawdown_pct": -13.38}, {"date": "2021-07-26", "drawdown_pct": -15.34}, {"date": "2021-08-02", "drawdown_pct": -12.28}, {"date": "2021-08-09", "drawdown_pct": -13.2}, {"date": "2021-08-16", "drawdown_pct": -17.1}, {"date": "2021-08-23", "drawdown_pct": -17.29}, {"date": "2021-08-30", "drawdown_pct": -17.84}, {"date": "2021-09-06", "drawdown_pct": -18.94}, {"date": "2021-09-13", "drawdown_pct": -19.79}, {"date": "2021-09-22", "drawdown_pct": -20.54}, {"date": "2021-09-29", "drawdown_pct": -20.27}, {"date": "2021-10-13", "drawdown_pct": -19.39}, {"date": "2021-10-20", "drawdown_pct": -17.51}, {"date": "2021-10-27", "drawdown_pct": -16.91}, {"date": "2021-11-03", "drawdown_pct": -16.45}, {"date": "2021-11-10", "drawdown_pct": -14.63}, {"date": "2021-11-17", "drawdown_pct": -14.09}, {"date": "2021-11-24", "drawdown_pct": -12.65}, {"date": "2021-12-01", "drawdown_pct": -12.78}, {"date": "2021-12-08", "drawdown_pct": -14.0}, {"date": "2021-12-15", "drawdown_pct": -12.99}, {"date": "2021-12-22", "drawdown_pct": -15.41}, {"date": "2021-12-29", "drawdown_pct": -17.59}, {"date": "2022-01-06", "drawdown_pct": -21.46}, {"date": "2022-01-13", "drawdown_pct": -22.58}, {"date": "2022-01-20", "drawdown_pct": -23.01}, {"date": "2022-01-27", "drawdown_pct": -27.01}, {"date": "2022-02-10", "drawdown_pct": -29.02}, {"date": "2022-02-17", "drawdown_pct": -28.69}, {"date": "2022-02-24", "drawdown_pct": -30.09}, {"date": "2022-03-03", "drawdown_pct": -29.89}, {"date": "2022-03-10", "drawdown_pct": -33.83}, {"date": "2022-03-17", "drawdown_pct": -31.93}, {"date": "2022-03-24", "drawdown_pct": -32.04}, {"date": "2022-03-31", "drawdown_pct": -33.22}, {"date": "2022-04-11", "drawdown_pct": -38.17}, {"date": "2022-04-18", "drawdown_pct": -37.53}, {"date": "2022-04-25", "drawdown_pct": -45.53}, {"date": "2022-05-05", "drawdown_pct": -42.53}, {"date": "2022-05-12", "drawdown_pct": -40.96}, {"date": "2022-05-19", "drawdown_pct": -40.31}, {"date": "2022-05-26", "drawdown_pct": -41.71}, {"date": "2022-06-02", "drawdown_pct": -38.27}, {"date": "2022-06-10", "drawdown_pct": -35.8}, {"date": "2022-06-17", "drawdown_pct": -33.27}, {"date": "2022-06-24", "drawdown_pct": -29.07}, {"date": "2022-07-01", "drawdown_pct": -30.14}, {"date": "2022-07-08", "drawdown_pct": -29.25}, {"date": "2022-07-15", "drawdown_pct": -30.68}, {"date": "2022-07-22", "drawdown_pct": -31.26}, {"date": "2022-07-29", "drawdown_pct": -32.94}, {"date": "2022-08-05", "drawdown_pct": -32.61}, {"date": "2022-08-12", "drawdown_pct": -32.43}, {"date": "2022-08-19", "drawdown_pct": -31.34}, {"date": "2022-08-26", "drawdown_pct": -33.7}, {"date": "2022-09-02", "drawdown_pct": -36.39}, {"date": "2022-09-09", "drawdown_pct": -36.01}, {"date": "2022-09-19", "drawdown_pct": -40.98}, {"date": "2022-09-26", "drawdown_pct": -41.66}, {"date": "2022-10-10", "drawdown_pct": -43.84}, {"date": "2022-10-17", "drawdown_pct": -38.85}, {"date": "2022-10-24", "drawdown_pct": -41.32}, {"date": "2022-10-31", "drawdown_pct": -43.12}, {"date": "2022-11-07", "drawdown_pct": -38.36}, {"date": "2022-11-14", "drawdown_pct": -40.36}, {"date": "2022-11-21", "drawdown_pct": -40.05}, {"date": "2022-11-28", "drawdown_pct": -42.27}, {"date": "2022-12-05", "drawdown_pct": -40.31}, {"date": "2022-12-12", "drawdown_pct": -39.69}, {"date": "2022-12-19", "drawdown_pct": -41.07}, {"date": "2022-12-26", "drawdown_pct": -41.45}, {"date": "2023-01-03", "drawdown_pct": -40.83}, {"date": "2023-01-10", "drawdown_pct": -37.87}, {"date": "2023-01-17", "drawdown_pct": -36.08}, {"date": "2023-01-31", "drawdown_pct": -35.19}, {"date": "2023-02-07", "drawdown_pct": -36.27}, {"date": "2023-02-14", "drawdown_pct": -35.59}, {"date": "2023-02-21", "drawdown_pct": -37.98}, {"date": "2023-02-28", "drawdown_pct": -39.0}, {"date": "2023-03-07", "drawdown_pct": -40.14}, {"date": "2023-03-14", "drawdown_pct": -41.16}, {"date": "2023-03-21", "drawdown_pct": -41.31}, {"date": "2023-03-28", "drawdown_pct": -40.51}, {"date": "2023-04-04", "drawdown_pct": -39.19}, {"date": "2023-04-12", "drawdown_pct": -39.0}, {"date": "2023-04-19", "drawdown_pct": -39.34}, {"date": "2023-04-26", "drawdown_pct": -42.39}, {"date": "2023-05-08", "drawdown_pct": -42.91}, {"date": "2023-05-15", "drawdown_pct": -42.25}, {"date": "2023-05-22", "drawdown_pct": -42.74}, {"date": "2023-05-29", "drawdown_pct": -44.66}, {"date": "2023-06-05", "drawdown_pct": -44.7}, {"date": "2023-06-12", "drawdown_pct": -45.95}, {"date": "2023-06-19", "drawdown_pct": -43.12}, {"date": "2023-06-28", "drawdown_pct": -45.2}, {"date": "2023-07-05", "drawdown_pct": -44.44}, {"date": "2023-07-12", "drawdown_pct": -44.83}, {"date": "2023-07-19", "drawdown_pct": -45.33}, {"date": "2023-07-26", "drawdown_pct": -44.98}, {"date": "2023-08-02", "drawdown_pct": -44.29}, {"date": "2023-08-09", "drawdown_pct": -44.03}, {"date": "2023-08-16", "drawdown_pct": -46.44}, {"date": "2023-08-23", "drawdown_pct": -48.8}, {"date": "2023-08-30", "drawdown_pct": -46.84}, {"date": "2023-09-06", "drawdown_pct": -47.23}, {"date": "2023-09-13", "drawdown_pct": -49.08}, {"date": "2023-09-20", "drawdown_pct": -50.1}, {"date": "2023-09-27", "drawdown_pct": -49.62}, {"date": "2023-10-12", "drawdown_pct": -49.3}, {"date": "2023-10-19", "drawdown_pct": -51.94}, {"date": "2023-10-26", "drawdown_pct": -52.89}, {"date": "2023-11-02", "drawdown_pct": -51.29}, {"date": "2023-11-09", "drawdown_pct": -49.32}, {"date": "2023-11-16", "drawdown_pct": -50.33}, {"date": "2023-11-23", "drawdown_pct": -50.75}, {"date": "2023-11-30", "drawdown_pct": -51.72}, {"date": "2023-12-07", "drawdown_pct": -52.86}, {"date": "2023-12-14", "drawdown_pct": -53.28}, {"date": "2023-12-21", "drawdown_pct": -53.98}, {"date": "2023-12-28", "drawdown_pct": -52.8}, {"date": "2024-01-05", "drawdown_pct": -55.41}, {"date": "2024-01-12", "drawdown_pct": -55.77}, {"date": "2024-01-19", "drawdown_pct": -56.92}, {"date": "2024-01-26", "drawdown_pct": -57.75}, {"date": "2024-02-02", "drawdown_pct": -61.07}, {"date": "2024-02-19", "drawdown_pct": -56.14}, {"date": "2024-02-26", "drawdown_pct": -56.01}, {"date": "2024-03-04", "drawdown_pct": -53.92}, {"date": "2024-03-11", "drawdown_pct": -52.53}, {"date": "2024-03-18", "drawdown_pct": -51.63}, {"date": "2024-03-25", "drawdown_pct": -53.96}, {"date": "2024-04-01", "drawdown_pct": -52.99}, {"date": "2024-04-10", "drawdown_pct": -55.05}, {"date": "2024-04-17", "drawdown_pct": -54.87}, {"date": "2024-04-24", "drawdown_pct": -55.67}, {"date": "2024-05-06", "drawdown_pct": -52.41}, {"date": "2024-05-13", "drawdown_pct": -53.28}, {"date": "2024-05-20", "drawdown_pct": -52.89}, {"date": "2024-05-27", "drawdown_pct": -54.02}, {"date": "2024-06-03", "drawdown_pct": -54.31}, {"date": "2024-06-11", "drawdown_pct": -55.12}, {"date": "2024-06-18", "drawdown_pct": -54.51}, {"date": "2024-06-25", "drawdown_pct": -57.31}, {"date": "2024-07-02", "drawdown_pct": -58.19}, {"date": "2024-07-09", "drawdown_pct": -58.51}, {"date": "2024-07-16", "drawdown_pct": -57.4}, {"date": "2024-07-23", "drawdown_pct": -58.03}, {"date": "2024-07-30", "drawdown_pct": -59.04}, {"date": "2024-08-06", "drawdown_pct": -59.13}, {"date": "2024-08-13", "drawdown_pct": -59.64}, {"date": "2024-08-20", "drawdown_pct": -60.63}, {"date": "2024-08-27", "drawdown_pct": -61.56}, {"date": "2024-09-03", "drawdown_pct": -60.92}, {"date": "2024-09-10", "drawdown_pct": -61.33}, {"date": "2024-09-19", "drawdown_pct": -61.17}, {"date": "2024-09-26", "drawdown_pct": -56.96}, {"date": "2024-10-10", "drawdown_pct": -44.43}, {"date": "2024-10-17", "drawdown_pct": -48.94}, {"date": "2024-10-24", "drawdown_pct": -45.38}, {"date": "2024-10-31", "drawdown_pct": -45.65}, {"date": "2024-11-07", "drawdown_pct": -40.97}, {"date": "2024-11-14", "drawdown_pct": -41.37}, {"date": "2024-11-21", "drawdown_pct": -43.1}, {"date": "2024-11-28", "drawdown_pct": -45.51}, {"date": "2024-12-05", "drawdown_pct": -44.22}, {"date": "2024-12-12", "drawdown_pct": -42.44}, {"date": "2024-12-19", "drawdown_pct": -44.41}, {"date": "2024-12-26", "drawdown_pct": -44.51}, {"date": "2025-01-03", "drawdown_pct": -49.38}, {"date": "2025-01-10", "drawdown_pct": -50.4}, {"date": "2025-01-17", "drawdown_pct": -48.09}, {"date": "2025-01-24", "drawdown_pct": -46.72}, {"date": "2025-02-10", "drawdown_pct": -45.16}, {"date": "2025-02-17", "drawdown_pct": -44.09}, {"date": "2025-02-24", "drawdown_pct": -43.09}, {"date": "2025-03-03", "drawdown_pct": -44.84}, {"date": "2025-03-10", "drawdown_pct": -44.76}, {"date": "2025-03-17", "drawdown_pct": -44.37}, {"date": "2025-03-24", "drawdown_pct": -45.95}, {"date": "2025-03-31", "drawdown_pct": -47.17}, {"date": "2025-04-08", "drawdown_pct": -53.79}, {"date": "2025-04-15", "drawdown_pct": -51.52}, {"date": "2025-04-22", "drawdown_pct": -51.57}, {"date": "2025-04-29", "drawdown_pct": -51.49}, {"date": "2025-05-09", "drawdown_pct": -49.48}, {"date": "2025-05-16", "drawdown_pct": -48.79}, {"date": "2025-05-23", "drawdown_pct": -49.24}, {"date": "2025-05-30", "drawdown_pct": -49.95}, {"date": "2025-06-09", "drawdown_pct": -48.24}, {"date": "2025-06-16", "drawdown_pct": -48.34}, {"date": "2025-06-23", "drawdown_pct": -49.33}, {"date": "2025-06-30", "drawdown_pct": -45.93}, {"date": "2025-07-07", "drawdown_pct": -46.51}, {"date": "2025-07-14", "drawdown_pct": -44.83}, {"date": "2025-07-21", "drawdown_pct": -42.32}, {"date": "2025-07-28", "drawdown_pct": -40.67}, {"date": "2025-08-04", "drawdown_pct": -41.38}, {"date": "2025-08-11", "drawdown_pct": -40.24}, {"date": "2025-08-18", "drawdown_pct": -34.55}, {"date": "2025-08-25", "drawdown_pct": -30.62}, {"date": "2025-09-01", "drawdown_pct": -25.76}, {"date": "2025-09-08", "drawdown_pct": -26.34}, {"date": "2025-09-15", "drawdown_pct": -23.0}, {"date": "2025-09-22", "drawdown_pct": -21.96}, {"date": "2025-09-29", "drawdown_pct": -18.69}, {"date": "2025-10-14", "drawdown_pct": -25.77}, {"date": "2025-10-21", "drawdown_pct": -22.56}, {"date": "2025-10-28", "drawdown_pct": -18.9}, {"date": "2025-11-04", "drawdown_pct": -21.3}, {"date": "2025-11-11", "drawdown_pct": -21.29}, {"date": "2025-11-18", "drawdown_pct": -22.93}, {"date": "2025-11-25", "drawdown_pct": -25.14}, {"date": "2025-12-02", "drawdown_pct": -22.88}, {"date": "2025-12-09", "drawdown_pct": -19.4}, {"date": "2025-12-16", "drawdown_pct": -22.86}, {"date": "2025-12-23", "drawdown_pct": -19.52}, {"date": "2025-12-30", "drawdown_pct": -18.57}, {"date": "2026-01-08", "drawdown_pct": -17.07}, {"date": "2026-01-15", "drawdown_pct": -15.43}, {"date": "2026-01-22", "drawdown_pct": -16.41}, {"date": "2026-01-29", "drawdown_pct": -17.02}, {"date": "2026-02-05", "drawdown_pct": -18.13}, {"date": "2026-02-12", "drawdown_pct": -16.43}, {"date": "2026-02-27", "drawdown_pct": -16.87}, {"date": "2026-03-06", "drawdown_pct": -18.91}, {"date": "2026-03-13", "drawdown_pct": -16.87}, {"date": "2026-03-20", "drawdown_pct": -15.82}, {"date": "2026-03-27", "drawdown_pct": -17.24}, {"date": "2026-04-03", "drawdown_pct": -20.91}, {"date": "2026-04-13", "drawdown_pct": -12.7}, {"date": "2026-04-20", "drawdown_pct": -7.65}, {"date": "2026-04-27", "drawdown_pct": -8.37}, {"date": "2026-05-07", "drawdown_pct": -3.75}, {"date": "2026-05-14", "drawdown_pct": -2.16}, {"date": "2026-05-21", "drawdown_pct": -5.16}, {"date": "2026-05-28", "drawdown_pct": 0.0}, {"date": "2026-06-04", "drawdown_pct": -0.88}, {"date": "2026-06-11", "drawdown_pct": -7.61}, {"date": "2026-06-18", "drawdown_pct": 0.0}, {"date": "2026-06-26", "drawdown_pct": -4.07}, {"date": "2026-07-03", "drawdown_pct": -8.05}, {"date": "2026-07-10", "drawdown_pct": -12.11}, {"date": "2026-07-17", "drawdown_pct": -21.58}], "named_events": [{"name": "回撤 (2010)", "category": "其他", "peak_date": "2010-06-11", "trough_date": "2010-07-05", "recovery_date": "2010-11-10", "drawdown_pct": -23.2, "recovery_days": 152}, {"name": "回撤 (2010)", "category": "其他", "peak_date": "2010-12-17", "trough_date": "2012-12-03", "recovery_date": "2013-08-26", "drawdown_pct": -51.9, "recovery_days": 983}, {"name": "回撤 (2013)", "category": "其他", "peak_date": "2013-10-09", "trough_date": "2013-12-05", "recovery_date": "2014-01-15", "drawdown_pct": -15.1, "recovery_days": 98}, {"name": "回撤 (2014)", "category": "其他", "peak_date": "2014-02-17", "trough_date": "2014-05-16", "recovery_date": "2014-10-08", "drawdown_pct": -21.3, "recovery_days": 233}, {"name": "回撤 (2014)", "category": "其他", "peak_date": "2014-12-15", "trough_date": "2014-12-30", "recovery_date": "2015-01-20", "drawdown_pct": -11.9, "recovery_days": 36}, {"name": "回撤 (2015)", "category": "其他", "peak_date": "2015-06-03", "trough_date": "2018-10-18", "recovery_date": "2026-05-13", "drawdown_pct": -69.7, "recovery_days": 3997}, {"name": "回撤 (2026)", "category": "其他", "peak_date": "2026-06-25", "trough_date": "2026-07-17", "recovery_date": null, "drawdown_pct": -21.6, "recovery_days": null}]}